[
    {
        "name": "Daniel Moreira",
        "link": "https://drive.google.com/thumbnail?id=1HxQFFoxxxSQU3atGONzQKEKdEoOY_ygl",
        "picture": "https://drive.google.com/thumbnail?id=1HxQFFoxxxSQU3atGONzQKEKdEoOY_ygl"
    },
    {
        "name": "Vivianny Khatly",
        "link": "https://www.linkedin.com/in/viviannykhatly/",
        "picture": "https://github.com/TailUFPB/tail-data/blob/main/images/Vivianny Khatly.jpeg"
    },
    {
        "name": "Ana Paula",
        "link": "https://www.linkedin.com/in/anapccabral/",
        "picture": "https://github.com/TailUFPB/tail-data/blob/main/images/Ana Paula.jpeg"
    },
    {
        "name": "Maria Moura",
        "link": "https://www.linkedin.com/in/mariam0ura/",
        "picture": "https://github.com/TailUFPB/tail-data/blob/main/images/Maria Moura.jpeg"
    },
    {
        "name": "Leudo Alves",
        "link": "https://www.linkedin.com/in/leudo-neto/",
        "picture": "https://github.com/TailUFPB/tail-data/blob/main/images/Leudo Neto.jpeg"
    },
    {
        "name": "Pedro Augusto",
        "link": "https://www.linkedin.com/in/pedro-augusto-medeiros-5a7388266/",
        "picture": "https://github.com/TailUFPB/tail-data/blob/main/images/Pedro Augusto Medeiro.jpeg"
    },
    {
        "name": "Victória Grisi",
        "link": "https://www.linkedin.com/in/victoria-grisi",
        "picture": "https://github.com/TailUFPB/tail-data/blob/main/images/Victória Grisi.jpeg"
    }
]